a2c_ppo_acktr/__init__.py
a2c_ppo_acktr/arguments.py
a2c_ppo_acktr/distributions.py
a2c_ppo_acktr/envs.py
a2c_ppo_acktr/model.py
a2c_ppo_acktr/storage.py
a2c_ppo_acktr/utils.py
a2c_ppo_acktr/visionmodel.py
a2c_ppo_acktr/algo/__init__.py
a2c_ppo_acktr/algo/a2c_acktr.py
a2c_ppo_acktr/algo/gail.py
a2c_ppo_acktr/algo/kfac.py
a2c_ppo_acktr/algo/ppo.py
curl_navi/CurriculumSchedulerMultiMachine.py
curl_navi/CurriculumSchedulerOneMachine.py
curl_navi/DifficultyVisualizer.py
curl_navi/DoorGym_gazebo_utils.py
curl_navi/DoorGym_utils.py
curl_navi/Evaluation.py
curl_navi/Evaluation_tools.py
curl_navi/None.py
curl_navi/PokingBot_inference.py
curl_navi/PokingBot_training.py
curl_navi/PokingBot_training_multi_machine.py
curl_navi/Train_env_analyze.py
curl_navi/Trajectories.py
curl_navi/__init__.py
curl_navi/_nbdev.py
curl_navi/card.py
curl_navi/core.py
curl_navi/environment_model.py
curl_navi/gym_environment.py
curl_navi/inference_result.py
curl_navi/model.py
curl_navi/model_utils.py
curl_navi/multi_machine_training_demo.py
curl_navi/multi_machine_training_tutorial.py
curl_navi/robot_model.py
curl_navi/wamv_inference.py
rlkit/__init__.py
rlkit/pythonplusplus.py
rlkit/core/__init__.py
rlkit/core/batch_rl_algorithm.py
rlkit/core/eval_util.py
rlkit/core/logging.py
rlkit/core/online_rl_algorithm.py
rlkit/core/rl_algorithm.py
rlkit/core/serializable.py
rlkit/core/tabulate.py
rlkit/core/trainer.py
rlkit/data_management/__init__.py
rlkit/data_management/env_replay_buffer.py
rlkit/data_management/normalizer.py
rlkit/data_management/obs_dict_replay_buffer.py
rlkit/data_management/online_vae_replay_buffer.py
rlkit/data_management/path_builder.py
rlkit/data_management/replay_buffer.py
rlkit/data_management/shared_obs_dict_replay_buffer.py
rlkit/data_management/simple_replay_buffer.py
rlkit/exploration_strategies/__init__.py
rlkit/exploration_strategies/base.py
rlkit/exploration_strategies/epsilon_greedy.py
rlkit/exploration_strategies/gaussian_and_epsilon_strategy.py
curl_navi-0.0.44.dist-info/LICENSE
curl_navi-0.0.44.dist-info/METADATA
curl_navi-0.0.44.dist-info/WHEEL
curl_navi-0.0.44.dist-info/entry_points.txt
curl_navi-0.0.44.dist-info/top_level.txt
curl_navi-0.0.44.dist-info/RECORD
