Metadata-Version: 2.1
Name: curl-navi
Version: 0.0.44
Summary: "A minimal example of nbdev using code from Allen Downey's Think Python 2nd Ed"
Home-page: https://github.com/yelloooowww/curl_navi/tree/master/
Author: yellow
Author-email: yellow.gdr09g@nctu.edu.tw
License: Apache Software License 2.0
Keywords: nbdev
Platform: UNKNOWN
Classifier: Development Status :: 3 - Alpha
Classifier: Intended Audience :: Developers
Classifier: Natural Language :: English
Classifier: Programming Language :: Python :: 3.6
Classifier: Programming Language :: Python :: 3.7
Classifier: Programming Language :: Python :: 3.8
Classifier: Programming Language :: Python :: 3.9
Classifier: Programming Language :: Python :: 3.10
Classifier: License :: OSI Approved :: Apache Software License
Requires-Python: >=3.6
License-File: LICENSE
Requires-Dist: pip
Requires-Dist: packaging
Provides-Extra: dev
